picai_eval/__init__.py
picai_eval/__main__.py
picai_eval/analysis_utils.py
picai_eval/data_utils.py
picai_eval/eval.py
picai_eval/image_utils.py
picai_eval/metrics.py
picai_eval/py.typed
picai_eval/statistical_helper.py
picai_eval/stat_util/stat_util.py
picai_eval-1.4.13.dist-info/LICENSE
picai_eval-1.4.13.dist-info/METADATA
picai_eval-1.4.13.dist-info/WHEEL
picai_eval-1.4.13.dist-info/top_level.txt
picai_eval-1.4.13.dist-info/RECORD
