Metadata-Version: 2.2
Name: picai_eval
Version: 1.4.13
Summary: PICAI Evaluation
Home-page: https://github.com/DIAGNijmegen/picai_eval
Author: Joeran Bosma, Anindo Saha and Matin Hosseinzadeh
Author-email: Joeran.Bosma@radboudumc.nl
License: Apache 2.0
Project-URL: Bug Tracker, https://github.com/DIAGNijmegen/picai_eval/issues
Platform: unix
Platform: linux
Platform: osx
Platform: cygwin
Platform: win32
Classifier: Programming Language :: Python :: 3
Classifier: Programming Language :: Python :: 3 :: Only
Classifier: Programming Language :: Python :: 3.9
Classifier: Programming Language :: Python :: 3.10
Classifier: Programming Language :: Python :: 3.11
Classifier: Programming Language :: Python :: 3.12
Classifier: Programming Language :: Python :: 3.13
Requires-Python: >=3.6
License-File: LICENSE
Requires-Dist: numpy
Requires-Dist: tqdm
Requires-Dist: SimpleITK
Requires-Dist: scipy
Requires-Dist: scikit-learn>=0.20.3
Requires-Dist: mlxtend
Requires-Dist: report_guided_annotation>=0.2.4
Provides-Extra: testing
Requires-Dist: pytest>=6.0; extra == "testing"
Requires-Dist: pytest-cov>=2.0; extra == "testing"
Requires-Dist: mypy>=0.910; extra == "testing"
Requires-Dist: flake8>=3.9; extra == "testing"
Requires-Dist: tox>=3.24; extra == "testing"
Dynamic: author-email
Dynamic: description
Dynamic: description-content-type
Dynamic: home-page
Dynamic: license
Dynamic: project-url
